questra_automation/__init__.py
questra_automation/client.py
questra_automation/_generated/graphql_client/__init__.py
questra_automation/_generated/graphql_client/async_base_client.py
questra_automation/_generated/graphql_client/automation_service_info.py
questra_automation/_generated/graphql_client/automations.py
questra_automation/_generated/graphql_client/base_model.py
questra_automation/_generated/graphql_client/client.py
questra_automation/_generated/graphql_client/create_repository.py
questra_automation/_generated/graphql_client/create_schedule.py
questra_automation/_generated/graphql_client/create_workspace.py
questra_automation/_generated/graphql_client/delete_repository.py
questra_automation/_generated/graphql_client/delete_schedule.py
questra_automation/_generated/graphql_client/delete_workspace.py
questra_automation/_generated/graphql_client/enums.py
questra_automation/_generated/graphql_client/error_codes.py
questra_automation/_generated/graphql_client/exceptions.py
questra_automation/_generated/graphql_client/execute_automation.py
questra_automation/_generated/graphql_client/executions.py
questra_automation/_generated/graphql_client/executions_without_output.py
questra_automation/_generated/graphql_client/input_types.py
questra_automation/_generated/graphql_client/renew_repository_ssh_key.py
questra_automation/_generated/graphql_client/repositories.py
questra_automation/_generated/graphql_client/scheduled_executions.py
questra_automation/_generated/graphql_client/schedules.py
questra_automation/_generated/graphql_client/synchronize_workspace.py
questra_automation/_generated/graphql_client/update_repository.py
questra_automation/_generated/graphql_client/update_schedule.py
questra_automation/_generated/graphql_client/update_workspace.py
questra_automation/_generated/graphql_client/workspaces.py
seven2one_questra_automation-0.1.3.dist-info/METADATA
seven2one_questra_automation-0.1.3.dist-info/WHEEL
seven2one_questra_automation-0.1.3.dist-info/RECORD
