Metadata-Version: 2.4
Name: seven2one-questra-automation
Version: 0.1.3
Summary: Questra Automation Python Package
Author-email: Jürgen Talasch <juergen.talasch@seven2one.de>
License: Proprietary
Classifier: Development Status :: 3 - Alpha
Classifier: Intended Audience :: Developers
Classifier: License :: Other/Proprietary License
Classifier: Programming Language :: Python :: 3
Classifier: Programming Language :: Python :: 3.10
Classifier: Programming Language :: Python :: 3.11
Classifier: Programming Language :: Python :: 3.12
Classifier: Programming Language :: Python :: 3.13
Classifier: Programming Language :: Python :: 3.14
Requires-Python: >=3.10
Requires-Dist: gql<4.0.0,>=3.5.0
Requires-Dist: httpx<1.0.0,>=0.28.1
Requires-Dist: loguru<1.0.0,>=0.7.0
Requires-Dist: pydantic<3.0.0,>=2.10.5
Requires-Dist: requests-toolbelt<2.0.0,>=1.0.0
Requires-Dist: seven2one-questra-authentication>=0.2.3
